{
  "people": [
    {
      "id": "1",
      "name": "Lorem Ipsadasum"
    },
    {
      "id": "2",
      "name": "Lorem Ipdassociatedsum"
    },
    {
      "id": "3",
      "name": "Lorem cxzero"
    },
    {
      "id": "4",
      "name": "Lorem cxz"
    },
    {
      "id": "5",
      "name": "Lorem Ipcxzczsum"
    },
    {
      "id": "6",
      "name": "Lorem Ipcxzcsum"
    },
    {
      "id": "7",
      "name": "Lorem Ipcxzczxcxzersum"
    },
    {
      "id": "8",
      "name": "Lorem cxz"
    },
    {
      "id": "9",
      "name": "Lorem Ipsufasm"
    },
    {
      "id": "10",
      "name": "Lorem Ipdasdsum"
    },
    {
      "id": "11",
      "name": "Lorem Ipssadasum"
    },
    {
      "id": "12",
      "name": "Lorem Ipsdasum"
    },
    {
      "id": "13",
      "name": "Lorem Ipdsasum"
    },
    {
      "id": "14",
      "name": "Lorem Ipfsafsum"
    },
    {
      "id": "15",
      "name": "Lorem Ipfassum"
    },
    {
      "id": "16",
      "name": "Lorem Ipfsasum"
    },
    {
      "id": "16",
      "name": "Lorem Ipfsasum"
    },
    {
      "id": "161",
      "name": "Lorem Ifaspsum"
    },
    {
      "id": "1622",
      "name": "Lorem Ipsfasum"
    },
    {
      "id": "1623",
      "name": "Lorem Ipsum"
    },
    {
      "id": "1624",
      "name": "Lorem Ipfassum"
    },
    {
      "id": "1625",
      "name": "Lorem Ipfsasum"
    },
    {
      "id": "1626",
      "name": "Lorem Ifsapsum"
    },
    {
      "id": "1627",
      "name": "Lorem Iphfgsum"
    },
    {
      "id": "1628",
      "name": "Lorem Ipgjsum"
    },
    {
      "id": "1629",
      "name": "Lorem Ipskgum"
    },
    {
      "id": "1620",
      "name": "Lorem Ipjhhfum"
    }
  ],
  "todos": [
    {
      "id": "1",
      "title": "Lorem Ipsum"
    },
    {
      "id": "01db",
      "title": "Sit Amet"
    }
  ]
}